mirp/__init__.py
mirp/config_data.xml
mirp/config_settings.xml
mirp/deep_learning_preprocessing.py
mirp/deprecated.py
mirp/extract_features_and_images.py
mirp/extract_image_parameters.py
mirp/extract_mask_labels.py
mirp/_data_import/__init__.py
mirp/_data_import/dicom_file.py
mirp/_data_import/dicom_file_cr.py
mirp/_data_import/dicom_file_ct.py
mirp/_data_import/dicom_file_dx.py
mirp/_data_import/dicom_file_mg.py
mirp/_data_import/dicom_file_mr.py
mirp/_data_import/dicom_file_mr_adc.py
mirp/_data_import/dicom_file_mr_dce.py
mirp/_data_import/dicom_file_pet.py
mirp/_data_import/dicom_file_rtdose.py
mirp/_data_import/dicom_file_rtstruct.py
mirp/_data_import/dicom_file_seg.py
mirp/_data_import/dicom_file_stack.py
mirp/_data_import/dicom_file_volume_stack.py
mirp/_data_import/dicom_multi_frame.py
mirp/_data_import/dicom_planar_image.py
mirp/_data_import/directory.py
mirp/_data_import/generic_file.py
mirp/_data_import/generic_file_stack.py
mirp/_data_import/itk_file.py
mirp/_data_import/itk_file_stack.py
mirp/_data_import/mask_contour.py
mirp/_data_import/numpy_file.py
mirp/_data_import/numpy_file_stack.py
mirp/_data_import/read_data.py
mirp/_data_import/suv.py
mirp/_data_import/utilities.py
mirp/_features/__init__.py
mirp/_features/base_feature.py
mirp/_features/cm_features.py
mirp/_features/cm_matrix.py
mirp/_features/dzm_features.py
mirp/_features/dzm_matrix.py
mirp/_features/feature_generator.py
mirp/_features/histogram.py
mirp/_features/ih_features.py
mirp/_features/ivh_features.py
mirp/_features/local_intensity_features.py
mirp/_features/morph_3d_data.py
mirp/_features/morph_3d_features.py
mirp/_features/ngldm_features.py
mirp/_features/ngldm_matrix.py
mirp/_features/ngtdm_features.py
mirp/_features/ngtdm_matrix.py
mirp/_features/rlm_features.py
mirp/_features/rlm_matrix.py
mirp/_features/stat_features.py
mirp/_features/szm_features.py
mirp/_features/szm_matrix.py
mirp/_features/texture_features.py
mirp/_features/texture_matrix.py
mirp/_features/utilities.py
mirp-2.4.2.dist-info/licenses/LICENSE.txt
mirp-2.4.2.dist-info/METADATA
mirp-2.4.2.dist-info/WHEEL
mirp-2.4.2.dist-info/top_level.txt
mirp-2.4.2.dist-info/RECORD
