Metadata-Version: 2.4
Name: mirp
Version: 2.4.2
Summary: A package for standardised processing of medical imaging and computation of quantitative features.
Author-email: Alex Zwanenburg <alexander.zwanenburg@nct-dresden.de>
License-Expression: EUPL-1.2
Project-URL: Repository, https://github.com/oncoray/mirp
Project-URL: Documentation, https://oncoray.github.io/mirp/
Project-URL: Changelog, https://github.com/oncoray/mirp/blob/master/NEWS.md
Classifier: Programming Language :: Python :: 3
Classifier: Programming Language :: Python :: 3.10
Classifier: Programming Language :: Python :: 3.11
Classifier: Programming Language :: Python :: 3.12
Classifier: Programming Language :: Python :: 3.13
Classifier: Operating System :: OS Independent
Classifier: Topic :: Scientific/Engineering :: Image Processing
Classifier: Topic :: Scientific/Engineering :: Medical Science Apps.
Requires-Python: >=3.10
License-File: LICENSE.txt
Requires-Dist: itk>=5.3.0
Requires-Dist: matplotlib>=3.7.0
Requires-Dist: numpy>=1.25
Requires-Dist: pandas>=2.0.0
Requires-Dist: pydicom>=2.4.0
Requires-Dist: pywavelets>=1.4.0
Requires-Dist: scikit-image>=0.20.0
Requires-Dist: scipy>=1.11
Requires-Dist: typing-extensions>=4.10; python_version < "3.11"
Provides-Extra: ray
Requires-Dist: ray>=2.34.0; extra == "ray"
Provides-Extra: joblib
Requires-Dist: joblib>=1.4.0; extra == "joblib"
Provides-Extra: test
Requires-Dist: pytest>=7.4.0; extra == "test"
Provides-Extra: docs
Requires-Dist: sphinx>=5.0.0; extra == "docs"
Requires-Dist: sphinx_rtd_theme>=2.0.0; extra == "docs"
Requires-Dist: nbsphinx; extra == "docs"
Dynamic: license-file
